Workbook

Sheet Dashboard
A1: Executive Financial Dashboard
A2: FY2025 | Consolidated from ERP Sales + General Ledger | Select a region in C4
B4: Region filter: | C4: All
J6: Monthly trend (selected region)
B7: Net Revenue | C7: Gross Profit | D7: GP Margin | E7: Transactions | F7: Avg Deal Size | G7: Budget Var % | H7: Recon Exceptions | J7: Month | K7: Revenue ($) | L7: Gross Profit ($)
B8: =SUMIFS(Data_Sales!$L$5:$L$1204,Data_Sales!$H$5:$H$1204,IF($C$4="All","*",$C$4)) | C8: =SUMIFS(Data_Sales!$M$5:$M$1204,Data_Sales!$H$5:$H$1204,IF($C$4="All","*",$C$4)) | D8: =IF(B8=0,0,C8/B8) | E8: =COUNTIFS(Data_Sales!$H$5:$H$1204,IF($C$4="All","*",$C$4)) | F8: =IF(E8=0,0,B8/E8) | G8: =Budget_vs_Actual!E17 | H8: =COUNTIF(Reconciliation!F5:F16,"Investigate") | J8: Jan | K8: =SUMIFS(Data_Sales!$L$5:$L$1204,Data_Sales!$G$5:$G$1204,J8,Data_Sales!$H$5:$H$1204,IF($C$4="All","*",$C$4)) | L8: =SUMIFS(Data_Sales!$M$5:$M$1204,Data_Sales!$G$5:$G$1204,J8,Data_Sales!$H$5:$H$1204,IF($C$4="All","*",$C$4))
J9: Feb | K9: =SUMIFS(Data_Sales!$L$5:$L$1204,Data_Sales!$G$5:$G$1204,J9,Data_Sales!$H$5:$H$1204,IF($C$4="All","*",$C$4)) | L9: =SUMIFS(Data_Sales!$M$5:$M$1204,Data_Sales!$G$5:$G$1204,J9,Data_Sales!$H$5:$H$1204,IF($C$4="All","*",$C$4))
J10: Mar | K10: =SUMIFS(Data_Sales!$L$5:$L$1204,Data_Sales!$G$5:$G$1204,J10,Data_Sales!$H$5:$H$1204,IF($C$4="All","*",$C$4)) | L10: =SUMIFS(Data_Sales!$M$5:$M$1204,Data_Sales!$G$5:$G$1204,J10,Data_Sales!$H$5:$H$1204,IF($C$4="All","*",$C$4))
J11: Apr | K11: =SUMIFS(Data_Sales!$L$5:$L$1204,Data_Sales!$G$5:$G$1204,J11,Data_Sales!$H$5:$H$1204,IF($C$4="All","*",$C$4)) | L11: =SUMIFS(Data_Sales!$M$5:$M$1204,Data_Sales!$G$5:$G$1204,J11,Data_Sales!$H$5:$H$1204,IF($C$4="All","*",$C$4))
J12: May | K12: =SUMIFS(Data_Sales!$L$5:$L$1204,Data_Sales!$G$5:$G$1204,J12,Data_Sales!$H$5:$H$1204,IF($C$4="All","*",$C$4)) | L12: =SUMIFS(Data_Sales!$M$5:$M$1204,Data_Sales!$G$5:$G$1204,J12,Data_Sales!$H$5:$H$1204,IF($C$4="All","*",$C$4))
J13: Jun | K13: =SUMIFS(Data_Sales!$L$5:$L$1204,Data_Sales!$G$5:$G$1204,J13,Data_Sales!$H$5:$H$1204,IF($C$4="All","*",$C$4)) | L13: =SUMIFS(Data_Sales!$M$5:$M$1204,Data_Sales!$G$5:$G$1204,J13,Data_Sales!$H$5:$H$1204,IF($C$4="All","*",$C$4))
J14: Jul | K14: =SUMIFS(Data_Sales!$L$5:$L$1204,Data_Sales!$G$5:$G$1204,J14,Data_Sales!$H$5:$H$1204,IF($C$4="All","*",$C$4)) | L14: =SUMIFS(Data_Sales!$M$5:$M$1204,Data_Sales!$G$5:$G$1204,J14,Data_Sales!$H$5:$H$1204,IF($C$4="All","*",$C$4))
J15: Aug | K15: =SUMIFS(Data_Sales!$L$5:$L$1204,Data_Sales!$G$5:$G$1204,J15,Data_Sales!$H$5:$H$1204,IF($C$4="All","*",$C$4)) | L15: =SUMIFS(Data_Sales!$M$5:$M$1204,Data_Sales!$G$5:$G$1204,J15,Data_Sales!$H$5:$H$1204,IF($C$4="All","*",$C$4))
J16: Sep | K16: =SUMIFS(Data_Sales!$L$5:$L$1204,Data_Sales!$G$5:$G$1204,J16,Data_Sales!$H$5:$H$1204,IF($C$4="All","*",$C$4)) | L16: =SUMIFS(Data_Sales!$M$5:$M$1204,Data_Sales!$G$5:$G$1204,J16,Data_Sales!$H$5:$H$1204,IF($C$4="All","*",$C$4))
J17: Oct | K17: =SUMIFS(Data_Sales!$L$5:$L$1204,Data_Sales!$G$5:$G$1204,J17,Data_Sales!$H$5:$H$1204,IF($C$4="All","*",$C$4)) | L17: =SUMIFS(Data_Sales!$M$5:$M$1204,Data_Sales!$G$5:$G$1204,J17,Data_Sales!$H$5:$H$1204,IF($C$4="All","*",$C$4))
J18: Nov | K18: =SUMIFS(Data_Sales!$L$5:$L$1204,Data_Sales!$G$5:$G$1204,J18,Data_Sales!$H$5:$H$1204,IF($C$4="All","*",$C$4)) | L18: =SUMIFS(Data_Sales!$M$5:$M$1204,Data_Sales!$G$5:$G$1204,J18,Data_Sales!$H$5:$H$1204,IF($C$4="All","*",$C$4))
J19: Dec | K19: =SUMIFS(Data_Sales!$L$5:$L$1204,Data_Sales!$G$5:$G$1204,J19,Data_Sales!$H$5:$H$1204,IF($C$4="All","*",$C$4)) | L19: =SUMIFS(Data_Sales!$M$5:$M$1204,Data_Sales!$G$5:$G$1204,J19,Data_Sales!$H$5:$H$1204,IF($C$4="All","*",$C$4))

Sheet Assumptions
A1: Forecast & Control Assumptions
A2: Blue cells are inputs - change them to run scenarios
A4: Driver | B4: Value | C4: Notes
A5: Monthly revenue growth | B5: 0.015 | C5: Applied month-over-month to forecast base
A6: Seasonality uplift (Q4) | B6: 0.08 | C6: Extra uplift for Oct-Dec
A7: Gross margin target | B7: 0.6 | C7: Target used for forecast gross profit
A8: Budget growth vs prior-year run-rate | B8: 0.05 | C8: Budget = avg actual x (1+growth)
A9: Reconciliation tolerance | B9: 0.01 | C9: Max allowed ERP vs GL difference
A10: Variance alert threshold | B10: 0.05 | C10: Flags variances beyond +/- this %

Sheet Lookups
A1: Master Data (Lookup Tables)
A2: Product master for VLOOKUP; region master for HLOOKUP
A4: Product ID | B4: Product Name | C4: Category | D4: Unit Price ($) | E4: Gross Margin % | G4: Region ID | H4: R01 | I4: R02 | J4: R03 | K4: R04
A5: P100 | B5: Analytics Suite | C5: Software | D5: 1200 | E5: 0.78 | G5: Region Name | H5: North | I5: South | J5: East | K5: West
A6: P200 | B6: Cloud Storage | C6: Services | D6: 450 | E6: 0.62 | G6: Regional Manager | H6: A. Sharma | I6: B. Patel | J6: C. Singh | K6: D. Rao
A7: P300 | B7: Consulting Hours | C7: Services | D7: 180 | E7: 0.45
A8: P400 | B8: Hardware Kit | C8: Hardware | D8: 950 | E8: 0.32
A9: P500 | B9: Support Plan | C9: Services | D9: 300 | E9: 0.7 | G9: Source: Synthetic demo master data generated by build_workbook.py
A10: P600 | B10: Training Pack | C10: Software | D10: 250 | E10: 0.66

Sheet Data_Sales
A1: Source 1: ERP Sales Transactions
A2: Blue = raw imported data; black = calculated enrichment columns
A4: Invoice | B4: Date | C4: Region ID | D4: Product ID | E4: Qty | F4: Discount % | G4: Month | H4: Region | I4: Product | J4: Category | K4: Unit Price | L4: Net Revenue | M4: Gross Profit
A5: INV-10729 | B5: 45658 | C5: R02 | D5: P300 | E5: 5 | F5: 0.05 | G5: =TEXT(B5,"mmm") | H5: =HLOOKUP(C5,Lookups!$H$4:$K$5,2,FALSE) | I5: =VLOOKUP(D5,Lookups!$A$5:$E$10,2,FALSE) | J5: =VLOOKUP(D5,Lookups!$A$5:$E$10,3,FALSE) | K5: =VLOOKUP(D5,Lookups!$A$5:$E$10,4,FALSE) | L5: =E5*K5*(1-F5) | M5: =L5*VLOOKUP(D5,Lookups!$A$5:$E$10,5,FALSE)
A6: INV-10745 | B6: 45658 | C6: R04 | D6: P100 | E6: 15 | F6: 0.1 | G6: =TEXT(B6,"mmm") | H6: =HLOOKUP(C6,Lookups!$H$4:$K$5,2,FALSE) | I6: =VLOOKUP(D6,Lookups!$A$5:$E$10,2,FALSE) | J6: =VLOOKUP(D6,Lookups!$A$5:$E$10,3,FALSE) | K6: =VLOOKUP(D6,Lookups!$A$5:$E$10,4,FALSE) | L6: =E6*K6*(1-F6) | M6: =L6*VLOOKUP(D6,Lookups!$A$5:$E$10,5,FALSE)
A7: INV-10030 | B7: 45659 | C7: R03 | D7: P600 | E7: 17 | F7: 0 | G7: =TEXT(B7,"mmm") | H7: =HLOOKUP(C7,Lookups!$H$4:$K$5,2,FALSE) | I7: =VLOOKUP(D7,Lookups!$A$5:$E$10,2,FALSE) | J7: =VLOOKUP(D7,Lookups!$A$5:$E$10,3,FALSE) | K7: =VLOOKUP(D7,Lookups!$A$5:$E$10,4,FALSE) | L7: =E7*K7*(1-F7) | M7: =L7*VLOOKUP(D7,Lookups!$A$5:$E$10,5,FALSE)
A8: INV-10481 | B8: 45659 | C8: R02 | D8: P600 | E8: 19 | F8: 0 | G8: =TEXT(B8,"mmm") | H8: =HLOOKUP(C8,Lookups!$H$4:$K$5,2,FALSE) | I8: =VLOOKUP(D8,Lookups!$A$5:$E$10,2,FALSE) | J8: =VLOOKUP(D8,Lookups!$A$5:$E$10,3,FALSE) | K8: =VLOOKUP(D8,Lookups!$A$5:$E$10,4,FALSE) | L8: =E8*K8*(1-F8) | M8: =L8*VLOOKUP(D8,Lookups!$A$5:$E$10,5,FALSE)
A9: INV-10850 | B9: 45659 | C9: R01 | D9: P100 | E9: 4 | F9: 0.1 | G9: =TEXT(B9,"mmm") | H9: =HLOOKUP(C9,Lookups!$H$4:$K$5,2,FALSE) | I9: =VLOOKUP(D9,Lookups!$A$5:$E$10,2,FALSE) | J9: =VLOOKUP(D9,Lookups!$A$5:$E$10,3,FALSE) | K9: =VLOOKUP(D9,Lookups!$A$5:$E$10,4,FALSE) | L9: =E9*K9*(1-F9) | M9: =L9*VLOOKUP(D9,Lookups!$A$5:$E$10,5,FALSE)
A10: INV-10881 | B10: 45659 | C10: R03 | D10: P300 | E10: 21 | F10: 0.05 | G10: =TEXT(B10,"mmm") | H10: =HLOOKUP(C10,Lookups!$H$4:$K$5,2,FALSE) | I10: =VLOOKUP(D10,Lookups!$A$5:$E$10,2,FALSE) | J10: =VLOOKUP(D10,Lookups!$A$5:$E$10,3,FALSE) | K10: =VLOOKUP(D10,Lookups!$A$5:$E$10,4,FALSE) | L10: =E10*K10*(1-F10) | M10: =L10*VLOOKUP(D10,Lookups!$A$5:$E$10,5,FALSE)
A11: INV-10825 | B11: 45660 | C11: R03 | D11: P400 | E11: 7 | F11: 0 | G11: =TEXT(B11,"mmm") | H11: =HLOOKUP(C11,Lookups!$H$4:$K$5,2,FALSE) | I11: =VLOOKUP(D11,Lookups!$A$5:$E$10,2,FALSE) | J11: =VLOOKUP(D11,Lookups!$A$5:$E$10,3,FALSE) | K11: =VLOOKUP(D11,Lookups!$A$5:$E$10,4,FALSE) | L11: =E11*K11*(1-F11) | M11: =L11*VLOOKUP(D11,Lookups!$A$5:$E$10,5,FALSE)
A12: INV-10941 | B12: 45660 | C12: R04 | D12: P500 | E12: 18 | F12: 0 | G12: =TEXT(B12,"mmm") | H12: =HLOOKUP(C12,Lookups!$H$4:$K$5,2,FALSE) | I12: =VLOOKUP(D12,Lookups!$A$5:$E$10,2,FALSE) | J12: =VLOOKUP(D12,Lookups!$A$5:$E$10,3,FALSE) | K12: =VLOOKUP(D12,Lookups!$A$5:$E$10,4,FALSE) | L12: =E12*K12*(1-F12) | M12: =L12*VLOOKUP(D12,Lookups!$A$5:$E$10,5,FALSE)
A13: INV-10997 | B13: 45660 | C13: R01 | D13: P600 | E13: 19 | F13: 0 | G13: =TEXT(B13,"mmm") | H13: =HLOOKUP(C13,Lookups!$H$4:$K$5,2,FALSE) | I13: =VLOOKUP(D13,Lookups!$A$5:$E$10,2,FALSE) | J13: =VLOOKUP(D13,Lookups!$A$5:$E$10,3,FALSE) | K13: =VLOOKUP(D13,Lookups!$A$5:$E$10,4,FALSE) | L13: =E13*K13*(1-F13) | M13: =L13*VLOOKUP(D13,Lookups!$A$5:$E$10,5,FALSE)
A14: INV-10042 | B14: 45661 | C14: R01 | D14: P100 | E14: 8 | F14: 0 | G14: =TEXT(B14,"mmm") | H14: =HLOOKUP(C14,Lookups!$H$4:$K$5,2,FALSE) | I14: =VLOOKUP(D14,Lookups!$A$5:$E$10,2,FALSE) | J14: =VLOOKUP(D14,Lookups!$A$5:$E$10,3,FALSE) | K14: =VLOOKUP(D14,Lookups!$A$5:$E$10,4,FALSE) | L14: =E14*K14*(1-F14) | M14: =L14*VLOOKUP(D14,Lookups!$A$5:$E$10,5,FALSE)
A15: INV-10282 | B15: 45661 | C15: R02 | D15: P200 | E15: 19 | F15: 0.1 | G15: =TEXT(B15,"mmm") | H15: =HLOOKUP(C15,Lookups!$H$4:$K$5,2,FALSE) | I15: =VLOOKUP(D15,Lookups!$A$5:$E$10,2,FALSE) | J15: =VLOOKUP(D15,Lookups!$A$5:$E$10,3,FALSE) | K15: =VLOOKUP(D15,Lookups!$A$5:$E$10,4,FALSE) | L15: =E15*K15*(1-F15) | M15: =L15*VLOOKUP(D15,Lookups!$A$5:$E$10,5,FALSE)
A16: INV-10292 | B16: 45661 | C16: R03 | D16: P200 | E16: 7 | F16: 0 | G16: =TEXT(B16,"mmm") | H16: =HLOOKUP(C16,Lookups!$H$4:$K$5,2,FALSE) | I16: =VLOOKUP(D16,Lookups!$A$5:$E$10,2,FALSE) | J16: =VLOOKUP(D16,Lookups!$A$5:$E$10,3,FALSE) | K16: =VLOOKUP(D16,Lookups!$A$5:$E$10,4,FALSE) | L16: =E16*K16*(1-F16) | M16: =L16*VLOOKUP(D16,Lookups!$A$5:$E$10,5,FALSE)
... A1204: INV-10802 | B1204: 46022 | C1204: R03 | D1204: P600 | E1204: 14 | F1204: 0.1 | G1204: =TEXT(B1204,"mmm") | H1204: =HLOOKUP(C1204,Lookups!$H$4:$K$5,2,FALSE) | I1204: =VLOOKUP(D1204,Lookups!$A$5:$E$10,2,FALSE) | J1204: =VLOOKUP(D1204,Lookups!$A$5:$E$10,3,FALSE) | K1204: =VLOOKUP(D1204,Lookups!$A$5:$E$10,4,FALSE) | L1204: =E1204*K1204*(1-F1204) | M1204: =L1204*VLOOKUP(D1204,Lookups!$A$5:$E$10,5,FALSE)

Sheet Data_GL
A1: Source 2: General Ledger Revenue Postings
A2: Month-end journal entries from finance system
A4: Journal ID | B4: Posting Date | C4: Region ID | D4: Account | E4: Amount ($) | F4: Month
A5: JE-R01-01 | B5: 45685 | C5: R01 | D5: 4000-Revenue | E5: 72841 | F5: =TEXT(B5,"mmm")
A6: JE-R01-02 | B6: 45716 | C6: R01 | D6: 4000-Revenue | E6: 149958 | F6: =TEXT(B6,"mmm")
A7: JE-R01-03 | B7: 45744 | C7: R01 | D7: 4000-Revenue | E7: 193256.5 | F7: =TEXT(B7,"mmm")
A8: JE-R01-04 | B8: 45775 | C8: R01 | D8: 4000-Revenue | E8: 133263.5 | F8: =TEXT(B8,"mmm")
A9: JE-R01-05 | B9: 45805 | C9: R01 | D9: 4000-Revenue | E9: 123942.32 | F9: =TEXT(B9,"mmm")
A10: JE-R01-06 | B10: 45836 | C10: R01 | D10: 4000-Revenue | E10: 228720 | F10: =TEXT(B10,"mmm")
A11: JE-R01-07 | B11: 45866 | C11: R01 | D11: 4000-Revenue | E11: 187469.93 | F11: =TEXT(B11,"mmm")
A12: JE-R01-08 | B12: 45897 | C12: R01 | D12: 4000-Revenue | E12: 200102 | F12: =TEXT(B12,"mmm")
A13: JE-R01-09 | B13: 45928 | C13: R01 | D13: 4000-Revenue | E13: 166111 | F13: =TEXT(B13,"mmm")
A14: JE-R01-10 | B14: 45958 | C14: R01 | D14: 4000-Revenue | E14: 247464.5 | F14: =TEXT(B14,"mmm")
A15: JE-R01-11 | B15: 45989 | C15: R01 | D15: 4000-Revenue | E15: 184219.5 | F15: =TEXT(B15,"mmm")
A16: JE-R01-12 | B16: 46019 | C16: R01 | D16: 4000-Revenue | E16: 151975.5 | F16: =TEXT(B16,"mmm")
... A52: JE-R04-12 | B52: 46019 | C52: R04 | D52: 4000-Revenue | E52: 187460 | F52: =TEXT(B52,"mmm")

Sheet Pivot_Summary
A1: Revenue Pivot: Region x Month ($)
A2: Pivot-style summary via SUMIFS (refresh-free); see VBA module for native PivotTable
A4: Region | B4: Jan | C4: Feb | D4: Mar | E4: Apr | F4: May | G4: Jun | H4: Jul | I4: Aug | J4: Sep | K4: Oct | L4: Nov | M4: Dec | N4: Total
A5: North | B5: =SUMIFS(Data_Sales!$L$5:$L$1204,Data_Sales!$H$5:$H$1204,$A5,Data_Sales!$G$5:$G$1204,"Jan") | C5: =SUMIFS(Data_Sales!$L$5:$L$1204,Data_Sales!$H$5:$H$1204,$A5,Data_Sales!$G$5:$G$1204,"Feb") | D5: =SUMIFS(Data_Sales!$L$5:$L$1204,Data_Sales!$H$5:$H$1204,$A5,Data_Sales!$G$5:$G$1204,"Mar") | E5: =SUMIFS(Data_Sales!$L$5:$L$1204,Data_Sales!$H$5:$H$1204,$A5,Data_Sales!$G$5:$G$1204,"Apr") | F5: =SUMIFS(Data_Sales!$L$5:$L$1204,Data_Sales!$H$5:$H$1204,$A5,Data_Sales!$G$5:$G$1204,"May") | G5: =SUMIFS(Data_Sales!$L$5:$L$1204,Data_Sales!$H$5:$H$1204,$A5,Data_Sales!$G$5:$G$1204,"Jun") | H5: =SUMIFS(Data_Sales!$L$5:$L$1204,Data_Sales!$H$5:$H$1204,$A5,Data_Sales!$G$5:$G$1204,"Jul") | I5: =SUMIFS(Data_Sales!$L$5:$L$1204,Data_Sales!$H$5:$H$1204,$A5,Data_Sales!$G$5:$G$1204,"Aug") | J5: =SUMIFS(Data_Sales!$L$5:$L$1204,Data_Sales!$H$5:$H$1204,$A5,Data_Sales!$G$5:$G$1204,"Sep") | K5: =SUMIFS(Data_Sales!$L$5:$L$1204,Data_Sales!$H$5:$H$1204,$A5,Data_Sales!$G$5:$G$1204,"Oct") | L5: =SUMIFS(Data_Sales!$L$5:$L$1204,Data_Sales!$H$5:$H$1204,$A5,Data_Sales!$G$5:$G$1204,"Nov") | M5: =SUMIFS(Data_Sales!$L$5:$L$1204,Data_Sales!$H$5:$H$1204,$A5,Data_Sales!$G$5:$G$1204,"Dec") | N5: =SUM(B5:M5)
A6: South | B6: =SUMIFS(Data_Sales!$L$5:$L$1204,Data_Sales!$H$5:$H$1204,$A6,Data_Sales!$G$5:$G$1204,"Jan") | C6: =SUMIFS(Data_Sales!$L$5:$L$1204,Data_Sales!$H$5:$H$1204,$A6,Data_Sales!$G$5:$G$1204,"Feb") | D6: =SUMIFS(Data_Sales!$L$5:$L$1204,Data_Sales!$H$5:$H$1204,$A6,Data_Sales!$G$5:$G$1204,"Mar") | E6: =SUMIFS(Data_Sales!$L$5:$L$1204,Data_Sales!$H$5:$H$1204,$A6,Data_Sales!$G$5:$G$1204,"Apr") | F6: =SUMIFS(Data_Sales!$L$5:$L$1204,Data_Sales!$H$5:$H$1204,$A6,Data_Sales!$G$5:$G$1204,"May") | G6: =SUMIFS(Data_Sales!$L$5:$L$1204,Data_Sales!$H$5:$H$1204,$A6,Data_Sales!$G$5:$G$1204,"Jun") | H6: =SUMIFS(Data_Sales!$L$5:$L$1204,Data_Sales!$H$5:$H$1204,$A6,Data_Sales!$G$5:$G$1204,"Jul") | I6: =SUMIFS(Data_Sales!$L$5:$L$1204,Data_Sales!$H$5:$H$1204,$A6,Data_Sales!$G$5:$G$1204,"Aug") | J6: =SUMIFS(Data_Sales!$L$5:$L$1204,Data_Sales!$H$5:$H$1204,$A6,Data_Sales!$G$5:$G$1204,"Sep") | K6: =SUMIFS(Data_Sales!$L$5:$L$1204,Data_Sales!$H$5:$H$1204,$A6,Data_Sales!$G$5:$G$1204,"Oct") | L6: =SUMIFS(Data_Sales!$L$5:$L$1204,Data_Sales!$H$5:$H$1204,$A6,Data_Sales!$G$5:$G$1204,"Nov") | M6: =SUMIFS(Data_Sales!$L$5:$L$1204,Data_Sales!$H$5:$H$1204,$A6,Data_Sales!$G$5:$G$1204,"Dec") | N6: =SUM(B6:M6)
A7: East | B7: =SUMIFS(Data_Sales!$L$5:$L$1204,Data_Sales!$H$5:$H$1204,$A7,Data_Sales!$G$5:$G$1204,"Jan") | C7: =SUMIFS(Data_Sales!$L$5:$L$1204,Data_Sales!$H$5:$H$1204,$A7,Data_Sales!$G$5:$G$1204,"Feb") | D7: =SUMIFS(Data_Sales!$L$5:$L$1204,Data_Sales!$H$5:$H$1204,$A7,Data_Sales!$G$5:$G$1204,"Mar") | E7: =SUMIFS(Data_Sales!$L$5:$L$1204,Data_Sales!$H$5:$H$1204,$A7,Data_Sales!$G$5:$G$1204,"Apr") | F7: =SUMIFS(Data_Sales!$L$5:$L$1204,Data_Sales!$H$5:$H$1204,$A7,Data_Sales!$G$5:$G$1204,"May") | G7: =SUMIFS(Data_Sales!$L$5:$L$1204,Data_Sales!$H$5:$H$1204,$A7,Data_Sales!$G$5:$G$1204,"Jun") | H7: =SUMIFS(Data_Sales!$L$5:$L$1204,Data_Sales!$H$5:$H$1204,$A7,Data_Sales!$G$5:$G$1204,"Jul") | I7: =SUMIFS(Data_Sales!$L$5:$L$1204,Data_Sales!$H$5:$H$1204,$A7,Data_Sales!$G$5:$G$1204,"Aug") | J7: =SUMIFS(Data_Sales!$L$5:$L$1204,Data_Sales!$H$5:$H$1204,$A7,Data_Sales!$G$5:$G$1204,"Sep") | K7: =SUMIFS(Data_Sales!$L$5:$L$1204,Data_Sales!$H$5:$H$1204,$A7,Data_Sales!$G$5:$G$1204,"Oct") | L7: =SUMIFS(Data_Sales!$L$5:$L$1204,Data_Sales!$H$5:$H$1204,$A7,Data_Sales!$G$5:$G$1204,"Nov") | M7: =SUMIFS(Data_Sales!$L$5:$L$1204,Data_Sales!$H$5:$H$1204,$A7,Data_Sales!$G$5:$G$1204,"Dec") | N7: =SUM(B7:M7)
A8: West | B8: =SUMIFS(Data_Sales!$L$5:$L$1204,Data_Sales!$H$5:$H$1204,$A8,Data_Sales!$G$5:$G$1204,"Jan") | C8: =SUMIFS(Data_Sales!$L$5:$L$1204,Data_Sales!$H$5:$H$1204,$A8,Data_Sales!$G$5:$G$1204,"Feb") | D8: =SUMIFS(Data_Sales!$L$5:$L$1204,Data_Sales!$H$5:$H$1204,$A8,Data_Sales!$G$5:$G$1204,"Mar") | E8: =SUMIFS(Data_Sales!$L$5:$L$1204,Data_Sales!$H$5:$H$1204,$A8,Data_Sales!$G$5:$G$1204,"Apr") | F8: =SUMIFS(Data_Sales!$L$5:$L$1204,Data_Sales!$H$5:$H$1204,$A8,Data_Sales!$G$5:$G$1204,"May") | G8: =SUMIFS(Data_Sales!$L$5:$L$1204,Data_Sales!$H$5:$H$1204,$A8,Data_Sales!$G$5:$G$1204,"Jun") | H8: =SUMIFS(Data_Sales!$L$5:$L$1204,Data_Sales!$H$5:$H$1204,$A8,Data_Sales!$G$5:$G$1204,"Jul") | I8: =SUMIFS(Data_Sales!$L$5:$L$1204,Data_Sales!$H$5:$H$1204,$A8,Data_Sales!$G$5:$G$1204,"Aug") | J8: =SUMIFS(Data_Sales!$L$5:$L$1204,Data_Sales!$H$5:$H$1204,$A8,Data_Sales!$G$5:$G$1204,"Sep") | K8: =SUMIFS(Data_Sales!$L$5:$L$1204,Data_Sales!$H$5:$H$1204,$A8,Data_Sales!$G$5:$G$1204,"Oct") | L8: =SUMIFS(Data_Sales!$L$5:$L$1204,Data_Sales!$H$5:$H$1204,$A8,Data_Sales!$G$5:$G$1204,"Nov") | M8: =SUMIFS(Data_Sales!$L$5:$L$1204,Data_Sales!$H$5:$H$1204,$A8,Data_Sales!$G$5:$G$1204,"Dec") | N8: =SUM(B8:M8)
A9: Total | B9: =SUM(B5:B8) | C9: =SUM(C5:C8) | D9: =SUM(D5:D8) | E9: =SUM(E5:E8) | F9: =SUM(F5:F8) | G9: =SUM(G5:G8) | H9: =SUM(H5:H8) | I9: =SUM(I5:I8) | ... N9: =SUM(N5:N8)
A11: Revenue & Gross Profit by Category
A12: Category | B12: Net Revenue ($) | C12: Gross Profit ($) | D12: GP Margin % | E12: Share of Revenue
A13: Hardware | B13: =SUMIF(Data_Sales!$J$5:$J$1204,A13,Data_Sales!$L$5:$L$1204) | C13: =SUMIF(Data_Sales!$J$5:$J$1204,A13,Data_Sales!$M$5:$M$1204) | D13: =IF(B13=0,0,C13/B13) | E13: =IF($N$9=0,0,B13/$N$9)
A14: Services | B14: =SUMIF(Data_Sales!$J$5:$J$1204,A14,Data_Sales!$L$5:$L$1204) | C14: =SUMIF(Data_Sales!$J$5:$J$1204,A14,Data_Sales!$M$5:$M$1204) | D14: =IF(B14=0,0,C14/B14) | E14: =IF($N$9=0,0,B14/$N$9)
A15: Software | B15: =SUMIF(Data_Sales!$J$5:$J$1204,A15,Data_Sales!$L$5:$L$1204) | C15: =SUMIF(Data_Sales!$J$5:$J$1204,A15,Data_Sales!$M$5:$M$1204) | D15: =IF(B15=0,0,C15/B15) | E15: =IF($N$9=0,0,B15/$N$9)

Sheet Reconciliation
A1: Monthly Reconciliation: ERP Sales vs General Ledger
A2: Automated tie-out with tolerance from Assumptions
A4: Month | B4: ERP Revenue ($) | C4: GL Revenue ($) | D4: Difference ($) | E4: Diff % | F4: Status
A5: Jan | B5: =SUMIF(Data_Sales!$G$5:$G$1204,A5,Data_Sales!$L$5:$L$1204) | C5: =SUMIF(Data_GL!$F$5:$F$52,A5,Data_GL!$E$5:$E$52) | D5: =C5-B5 | E5: =IF(B5=0,0,D5/B5) | F5: =IF(ABS(E5)<=Assumptions!$B$9,"Reconciled","Investigate")
A6: Feb | B6: =SUMIF(Data_Sales!$G$5:$G$1204,A6,Data_Sales!$L$5:$L$1204) | C6: =SUMIF(Data_GL!$F$5:$F$52,A6,Data_GL!$E$5:$E$52) | D6: =C6-B6 | E6: =IF(B6=0,0,D6/B6) | F6: =IF(ABS(E6)<=Assumptions!$B$9,"Reconciled","Investigate")
A7: Mar | B7: =SUMIF(Data_Sales!$G$5:$G$1204,A7,Data_Sales!$L$5:$L$1204) | C7: =SUMIF(Data_GL!$F$5:$F$52,A7,Data_GL!$E$5:$E$52) | D7: =C7-B7 | E7: =IF(B7=0,0,D7/B7) | F7: =IF(ABS(E7)<=Assumptions!$B$9,"Reconciled","Investigate")
A8: Apr | B8: =SUMIF(Data_Sales!$G$5:$G$1204,A8,Data_Sales!$L$5:$L$1204) | C8: =SUMIF(Data_GL!$F$5:$F$52,A8,Data_GL!$E$5:$E$52) | D8: =C8-B8 | E8: =IF(B8=0,0,D8/B8) | F8: =IF(ABS(E8)<=Assumptions!$B$9,"Reconciled","Investigate")
A9: May | B9: =SUMIF(Data_Sales!$G$5:$G$1204,A9,Data_Sales!$L$5:$L$1204) | C9: =SUMIF(Data_GL!$F$5:$F$52,A9,Data_GL!$E$5:$E$52) | D9: =C9-B9 | E9: =IF(B9=0,0,D9/B9) | F9: =IF(ABS(E9)<=Assumptions!$B$9,"Reconciled","Investigate")
A10: Jun | B10: =SUMIF(Data_Sales!$G$5:$G$1204,A10,Data_Sales!$L$5:$L$1204) | C10: =SUMIF(Data_GL!$F$5:$F$52,A10,Data_GL!$E$5:$E$52) | D10: =C10-B10 | E10: =IF(B10=0,0,D10/B10) | F10: =IF(ABS(E10)<=Assumptions!$B$9,"Reconciled","Investigate")
A11: Jul | B11: =SUMIF(Data_Sales!$G$5:$G$1204,A11,Data_Sales!$L$5:$L$1204) | C11: =SUMIF(Data_GL!$F$5:$F$52,A11,Data_GL!$E$5:$E$52) | D11: =C11-B11 | E11: =IF(B11=0,0,D11/B11) | F11: =IF(ABS(E11)<=Assumptions!$B$9,"Reconciled","Investigate")
A12: Aug | B12: =SUMIF(Data_Sales!$G$5:$G$1204,A12,Data_Sales!$L$5:$L$1204) | C12: =SUMIF(Data_GL!$F$5:$F$52,A12,Data_GL!$E$5:$E$52) | D12: =C12-B12 | E12: =IF(B12=0,0,D12/B12) | F12: =IF(ABS(E12)<=Assumptions!$B$9,"Reconciled","Investigate")
A13: Sep | B13: =SUMIF(Data_Sales!$G$5:$G$1204,A13,Data_Sales!$L$5:$L$1204) | C13: =SUMIF(Data_GL!$F$5:$F$52,A13,Data_GL!$E$5:$E$52) | D13: =C13-B13 | E13: =IF(B13=0,0,D13/B13) | F13: =IF(ABS(E13)<=Assumptions!$B$9,"Reconciled","Investigate")
A14: Oct | B14: =SUMIF(Data_Sales!$G$5:$G$1204,A14,Data_Sales!$L$5:$L$1204) | C14: =SUMIF(Data_GL!$F$5:$F$52,A14,Data_GL!$E$5:$E$52) | D14: =C14-B14 | E14: =IF(B14=0,0,D14/B14) | F14: =IF(ABS(E14)<=Assumptions!$B$9,"Reconciled","Investigate")
A15: Nov | B15: =SUMIF(Data_Sales!$G$5:$G$1204,A15,Data_Sales!$L$5:$L$1204) | C15: =SUMIF(Data_GL!$F$5:$F$52,A15,Data_GL!$E$5:$E$52) | D15: =C15-B15 | E15: =IF(B15=0,0,D15/B15) | F15: =IF(ABS(E15)<=Assumptions!$B$9,"Reconciled","Investigate")
A16: Dec | B16: =SUMIF(Data_Sales!$G$5:$G$1204,A16,Data_Sales!$L$5:$L$1204) | C16: =SUMIF(Data_GL!$F$5:$F$52,A16,Data_GL!$E$5:$E$52) | D16: =C16-B16 | E16: =IF(B16=0,0,D16/B16) | F16: =IF(ABS(E16)<=Assumptions!$B$9,"Reconciled","Investigate")
A17: Total | B17: =SUM(B5:B16) | C17: =SUM(C5:C16) | D17: =SUM(D5:D16) | E17: =IF(B17=0,0,D17/B17) | F17: =COUNTIF(F5:F16,"Investigate")&" exception(s)"

Sheet Budget_vs_Actual
A1: Budget vs Actual - Variance Analysis
A2: Budget derived from Assumptions; variances flagged vs alert threshold
A4: Month | B4: Actual ($) | C4: Budget ($) | D4: Variance ($) | E4: Variance % | F4: Flag | G4: YTD Actual ($) | H4: YTD Budget ($) | I4: YTD Var %
A5: Jan | B5: =Pivot_Summary!B9 | C5: =ROUND(AVERAGE(Pivot_Summary!$B$9:$M$9)*(1+Assumptions!$B$8),-2) | D5: =B5-C5 | E5: =IF(C5=0,0,D5/C5) | F5: =IF(E5>Assumptions!$B$10,"Above",IF(E5<-Assumptions!$B$10,"Below","On Track")) | G5: =SUM($B$5:B5) | H5: =SUM($C$5:C5) | I5: =IF(H5=0,0,G5/H5-1)
A6: Feb | B6: =Pivot_Summary!C9 | C6: =ROUND(AVERAGE(Pivot_Summary!$B$9:$M$9)*(1+Assumptions!$B$8),-2) | D6: =B6-C6 | E6: =IF(C6=0,0,D6/C6) | F6: =IF(E6>Assumptions!$B$10,"Above",IF(E6<-Assumptions!$B$10,"Below","On Track")) | G6: =SUM($B$5:B6) | H6: =SUM($C$5:C6) | I6: =IF(H6=0,0,G6/H6-1)
A7: Mar | B7: =Pivot_Summary!D9 | C7: =ROUND(AVERAGE(Pivot_Summary!$B$9:$M$9)*(1+Assumptions!$B$8),-2) | D7: =B7-C7 | E7: =IF(C7=0,0,D7/C7) | F7: =IF(E7>Assumptions!$B$10,"Above",IF(E7<-Assumptions!$B$10,"Below","On Track")) | G7: =SUM($B$5:B7) | H7: =SUM($C$5:C7) | I7: =IF(H7=0,0,G7/H7-1)
A8: Apr | B8: =Pivot_Summary!E9 | C8: =ROUND(AVERAGE(Pivot_Summary!$B$9:$M$9)*(1+Assumptions!$B$8),-2) | D8: =B8-C8 | E8: =IF(C8=0,0,D8/C8) | F8: =IF(E8>Assumptions!$B$10,"Above",IF(E8<-Assumptions!$B$10,"Below","On Track")) | G8: =SUM($B$5:B8) | H8: =SUM($C$5:C8) | I8: =IF(H8=0,0,G8/H8-1)
A9: May | B9: =Pivot_Summary!F9 | C9: =ROUND(AVERAGE(Pivot_Summary!$B$9:$M$9)*(1+Assumptions!$B$8),-2) | D9: =B9-C9 | E9: =IF(C9=0,0,D9/C9) | F9: =IF(E9>Assumptions!$B$10,"Above",IF(E9<-Assumptions!$B$10,"Below","On Track")) | G9: =SUM($B$5:B9) | H9: =SUM($C$5:C9) | I9: =IF(H9=0,0,G9/H9-1)
A10: Jun | B10: =Pivot_Summary!G9 | C10: =ROUND(AVERAGE(Pivot_Summary!$B$9:$M$9)*(1+Assumptions!$B$8),-2) | D10: =B10-C10 | E10: =IF(C10=0,0,D10/C10) | F10: =IF(E10>Assumptions!$B$10,"Above",IF(E10<-Assumptions!$B$10,"Below","On Track")) | G10: =SUM($B$5:B10) | H10: =SUM($C$5:C10) | I10: =IF(H10=0,0,G10/H10-1)
A11: Jul | B11: =Pivot_Summary!H9 | C11: =ROUND(AVERAGE(Pivot_Summary!$B$9:$M$9)*(1+Assumptions!$B$8),-2) | D11: =B11-C11 | E11: =IF(C11=0,0,D11/C11) | F11: =IF(E11>Assumptions!$B$10,"Above",IF(E11<-Assumptions!$B$10,"Below","On Track")) | G11: =SUM($B$5:B11) | H11: =SUM($C$5:C11) | I11: =IF(H11=0,0,G11/H11-1)
A12: Aug | B12: =Pivot_Summary!I9 | C12: =ROUND(AVERAGE(Pivot_Summary!$B$9:$M$9)*(1+Assumptions!$B$8),-2) | D12: =B12-C12 | E12: =IF(C12=0,0,D12/C12) | F12: =IF(E12>Assumptions!$B$10,"Above",IF(E12<-Assumptions!$B$10,"Below","On Track")) | G12: =SUM($B$5:B12) | H12: =SUM($C$5:C12) | I12: =IF(H12=0,0,G12/H12-1)
A13: Sep | B13: =Pivot_Summary!J9 | C13: =ROUND(AVERAGE(Pivot_Summary!$B$9:$M$9)*(1+Assumptions!$B$8),-2) | D13: =B13-C13 | E13: =IF(C13=0,0,D13/C13) | F13: =IF(E13>Assumptions!$B$10,"Above",IF(E13<-Assumptions!$B$10,"Below","On Track")) | G13: =SUM($B$5:B13) | H13: =SUM($C$5:C13) | I13: =IF(H13=0,0,G13/H13-1)
A14: Oct | B14: =Pivot_Summary!K9 | C14: =ROUND(AVERAGE(Pivot_Summary!$B$9:$M$9)*(1+Assumptions!$B$8),-2) | D14: =B14-C14 | E14: =IF(C14=0,0,D14/C14) | F14: =IF(E14>Assumptions!$B$10,"Above",IF(E14<-Assumptions!$B$10,"Below","On Track")) | G14: =SUM($B$5:B14) | H14: =SUM($C$5:C14) | I14: =IF(H14=0,0,G14/H14-1)
A15: Nov | B15: =Pivot_Summary!L9 | C15: =ROUND(AVERAGE(Pivot_Summary!$B$9:$M$9)*(1+Assumptions!$B$8),-2) | D15: =B15-C15 | E15: =IF(C15=0,0,D15/C15) | F15: =IF(E15>Assumptions!$B$10,"Above",IF(E15<-Assumptions!$B$10,"Below","On Track")) | G15: =SUM($B$5:B15) | H15: =SUM($C$5:C15) | I15: =IF(H15=0,0,G15/H15-1)
A16: Dec | B16: =Pivot_Summary!M9 | C16: =ROUND(AVERAGE(Pivot_Summary!$B$9:$M$9)*(1+Assumptions!$B$8),-2) | D16: =B16-C16 | E16: =IF(C16=0,0,D16/C16) | F16: =IF(E16>Assumptions!$B$10,"Above",IF(E16<-Assumptions!$B$10,"Below","On Track")) | G16: =SUM($B$5:B16) | H16: =SUM($C$5:C16) | I16: =IF(H16=0,0,G16/H16-1)
A17: Total | B17: =SUM(B5:B16) | C17: =SUM(C5:C16) | D17: =SUM(D5:D16) | E17: =IF(C17=0,0,D17/C17)

Sheet Forecast
A1: 12-Month Rolling Forecast (2026)
A2: Base = last-3-month average actual; driven by Assumptions
A4: Forecast base (avg last 3 months actual) | D4: =AVERAGE(Budget_vs_Actual!B14:B16)
A6: Month | B6: Period # | C6: Forecast Revenue ($) | D6: Forecast GP ($) | E6: Cumulative Revenue ($) | F6: MoM Growth %
A7: Jan-26 | B7: 1 | C7: =$D$4*(1+Assumptions!$B$5)^B7*IF(B7>=10,1+Assumptions!$B$6,1) | D7: =C7*Assumptions!$B$7 | E7: =SUM($C$7:C7) | F7: =0
A8: Feb-26 | B8: 2 | C8: =$D$4*(1+Assumptions!$B$5)^B8*IF(B8>=10,1+Assumptions!$B$6,1) | D8: =C8*Assumptions!$B$7 | E8: =SUM($C$7:C8) | F8: =IF(C7=0,0,C8/C7-1)
A9: Mar-26 | B9: 3 | C9: =$D$4*(1+Assumptions!$B$5)^B9*IF(B9>=10,1+Assumptions!$B$6,1) | D9: =C9*Assumptions!$B$7 | E9: =SUM($C$7:C9) | F9: =IF(C8=0,0,C9/C8-1)
A10: Apr-26 | B10: 4 | C10: =$D$4*(1+Assumptions!$B$5)^B10*IF(B10>=10,1+Assumptions!$B$6,1) | D10: =C10*Assumptions!$B$7 | E10: =SUM($C$7:C10) | F10: =IF(C9=0,0,C10/C9-1)
A11: May-26 | B11: 5 | C11: =$D$4*(1+Assumptions!$B$5)^B11*IF(B11>=10,1+Assumptions!$B$6,1) | D11: =C11*Assumptions!$B$7 | E11: =SUM($C$7:C11) | F11: =IF(C10=0,0,C11/C10-1)
A12: Jun-26 | B12: 6 | C12: =$D$4*(1+Assumptions!$B$5)^B12*IF(B12>=10,1+Assumptions!$B$6,1) | D12: =C12*Assumptions!$B$7 | E12: =SUM($C$7:C12) | F12: =IF(C11=0,0,C12/C11-1)
A13: Jul-26 | B13: 7 | C13: =$D$4*(1+Assumptions!$B$5)^B13*IF(B13>=10,1+Assumptions!$B$6,1) | D13: =C13*Assumptions!$B$7 | E13: =SUM($C$7:C13) | F13: =IF(C12=0,0,C13/C12-1)
A14: Aug-26 | B14: 8 | C14: =$D$4*(1+Assumptions!$B$5)^B14*IF(B14>=10,1+Assumptions!$B$6,1) | D14: =C14*Assumptions!$B$7 | E14: =SUM($C$7:C14) | F14: =IF(C13=0,0,C14/C13-1)
A15: Sep-26 | B15: 9 | C15: =$D$4*(1+Assumptions!$B$5)^B15*IF(B15>=10,1+Assumptions!$B$6,1) | D15: =C15*Assumptions!$B$7 | E15: =SUM($C$7:C15) | F15: =IF(C14=0,0,C15/C14-1)
A16: Oct-26 | B16: 10 | C16: =$D$4*(1+Assumptions!$B$5)^B16*IF(B16>=10,1+Assumptions!$B$6,1) | D16: =C16*Assumptions!$B$7 | E16: =SUM($C$7:C16) | F16: =IF(C15=0,0,C16/C15-1)
A17: Nov-26 | B17: 11 | C17: =$D$4*(1+Assumptions!$B$5)^B17*IF(B17>=10,1+Assumptions!$B$6,1) | D17: =C17*Assumptions!$B$7 | E17: =SUM($C$7:C17) | F17: =IF(C16=0,0,C17/C16-1)
A18: Dec-26 | B18: 12 | C18: =$D$4*(1+Assumptions!$B$5)^B18*IF(B18>=10,1+Assumptions!$B$6,1) | D18: =C18*Assumptions!$B$7 | E18: =SUM($C$7:C18) | F18: =IF(C17=0,0,C18/C17-1)
A19: Total | C19: =SUM(C7:C18) | D19: =SUM(D7:D18)
